Metadata-Version: 2.1
Name: ilyaLR33
Version: 0.2.0
Summary: https://github.com/m3smerized/prog5lr3
Author: Ilya
Author-email: ikinyaev2004@mail.ru
Requires-Python: >=3.6
